expyDB/__init__.py
expyDB/database_model.py
expyDB/database_operations.py
expyDB/database_queries.py
expyDB/intervention_model.py
expydb-0.6.2.dist-info/licenses/LICENSE
tests/__init__.py
tests/test_intervention_model.py
expydb-0.6.2.dist-info/METADATA
expydb-0.6.2.dist-info/WHEEL
expydb-0.6.2.dist-info/top_level.txt
expydb-0.6.2.dist-info/RECORD
