Metadata-Version: 2.4
Name: expyDB
Version: 0.6.2
Summary: Set up and maintain databases for handling experimental data in Python
Author-email: Florian Schunck <fluncki@protonmail.com>
License:                     GNU GENERAL PUBLIC LICENSE
Project-URL: Homepage, https://github.com/flo-schu/expyDB
Classifier: Programming Language :: Python :: 3
Classifier: Natural Language :: English
Classifier: License :: OSI Approved :: GNU General Public License v3 (GPLv3)
Classifier: Topic :: Scientific/Engineering :: Bio-Informatics
Requires-Python: >=3.10
License-File: LICENSE
Requires-Dist: sqlalchemy>=2.0
Requires-Dist: sqlmodel==0.0.22
Requires-Dist: numpy>=1.24.0
Requires-Dist: pandas>=2.0.2
Requires-Dist: xarray
Requires-Dist: arviz
Provides-Extra: dev
Requires-Dist: black; extra == "dev"
Requires-Dist: pytest; extra == "dev"
Requires-Dist: bumpver; extra == "dev"
Dynamic: license-file
